g2p_using_rnn/__init__.py
g2p_using_rnn/create_train_test_data.py
g2p_using_rnn/handle_missing_words_in_lexicon.py
g2p_using_rnn/predict_on_single_sequence.py
g2p_using_rnn/predict_using_rnn.py
g2p_using_rnn/s2s_model_updated_data1_e2e.keras
g2p_using_rnn/train_rnn.py
g2p_using_rnn/transform_test_data_from_different_source.py
g2p_using_rnn/version_control_lexicon_update_10_LDist_test.txt
g2p_using_rnn/version_control_lexicon_update_10_LDist_train.txt
g2p_using_rnn-0.0.1.dist-info/METADATA
g2p_using_rnn-0.0.1.dist-info/WHEEL
g2p_using_rnn-0.0.1.dist-info/licenses/LICENSE
g2p_using_rnn-0.0.1.dist-info/RECORD
