Metadata-Version: 2.3
Name: g2p_using_rnn
Version: 0.0.1
Summary: A small example package to use RNN models for Grapheme to Phoneme conversion
Author-email: Soumya Barikeri <soumyabarikeri@gmail.com>
License-File: LICENSE
Classifier: License :: OSI Approved :: MIT License
Classifier: Operating System :: OS Independent
Classifier: Programming Language :: Python :: 3
Requires-Python: >=3.10
